README.md
setup.py
jogger/__init__.py
jogger.egg-info/PKG-INFO
jogger.egg-info/SOURCES.txt
jogger.egg-info/dependency_links.txt
jogger.egg-info/requires.txt
jogger.egg-info/top_level.txt