Metadata-Version: 1.1
Name: jogger
Version: 0.1.0
Summary: Simple tool for an advanced logging experience
Home-page: https://gitlab.com/xneomac/jogger
Author: Noel Martignoni
Author-email: noel@martignoni.fr
License: UNKNOWN
Platform: UNKNOWN
Classifier: Development Status :: 2 - Pre-Alpha
Classifier: Environment :: Console
Classifier: Intended Audience :: Developers
Classifier: Intended Audience :: System Administrators
Classifier: License :: OSI Approved :: BSD License
Classifier: Operating System :: POSIX :: Linux
Classifier: Programming Language :: Python
Classifier: Topic :: System :: Logging
Classifier: Topic :: Utilities
